{"published": "2015-09-15T14:45:05Z", "media-type": "Blog", "title": "Warriors Come Back to Play for Coney Island Reunion", "id": "96d6d10c-ed32-4a1b-9d3f-c430c2e84a9e", "content": "A reunion of the cast of the 1979 cult classic The Warriors drew more than 5,000 fans to the film\u2019s original setting of Coney Island on Sunday. Fans dressed up like the Warriors and their rival gangs, transforming Coney Island into a campy, gritty gangland\u00a0straight out of the movie.\n\n\n. @SOIANYC\u2026", "source": "Brownstoner \u00bb \u00bbBrownstoner"}