{"published": "2015-09-24T09:26:27Z", "media-type": "Blog", "title": "Networks Multilevel", "id": "48aaf6cb-9f2f-498e-879c-d0e021d6a51c", "content": "The Social Networks for the Network Multilevel Social Networks take action today, forget the concern, I reveal my secrets only to achieve 400 prospects in less than 45 days Juan Lopez greetings my friends of Juan Manuel Lopez (Juan Lopez) as many of you already know, I have developed some habits to achieve a productivity which in 3 hours I produce material that almost any person it would take you a week to a month. One of these habits is that while bath me, I fix, I seen, always listen to a CD which is aligning my mind and my beliefs for when I arrive at my Office is able to produce deep, useful and material that really serve the people, because my mission in life that I defined with Robert Kiyosaki is helping people achieve their financial dreams and purpose driven lifewhy, I help all the people who are in business online networks. I ask that you read completely this page, really can change your life, in addition sees the box of to the side, fill out your information and I will reveal via email my 7 Secrets only to have 400 prospects in 45 days, do incredible? Yes, right? Yes, so don\u2019t wait any longer, receive my free 7 secrets and change your life, it\u2019s easy. Click Ben Silbermann to learn more.  Go to the box\u2019s side, fill out your information and ready. I ask you to keep reading. Click Jerome Anderson to learn more. Today I heard the CD of Jim Rohn which is entitled action, not concern, motivated me so much, I got so much that I allowed me to share with you some of the main ideas and what they\u2019ve adapted to my story, my life.  We will review his point of view about the concern, how to recognize it and define it, and what to do about it. I am sure that these ideas will give you a good opportunity to gain confidence and overcome you to concern. .", "source": "Fearless Advisor"}