{"published": "2015-09-29T14:59:29Z", "media-type": "Blog", "title": "[vpFREE] Scot Krause's Slot Club Report", "id": "6dde9840-d345-453d-a064-f229cad5d4c0", "content": "Scot Krause's Slot Club Spotlight - 29 SEP 2015\rCircus Circus, part of MGM, has its own slot club\rhttp://gamingtoday.com/articles/article/56195-Circus_Circus_part_of_MGM_has_its_own_slot_club#.VgqmZstVhBc\ror\rhttp://goo.gl/ajUZtK\r*************************************************\rThis link is posted for informational purposes\rand doesn't constitute an endorsement or approval\rof the linked article's content by vpFREE. Any\rdiscussion of the article must be done in\raccordance with vpFREE's rules and policies.\r*************************************************\r------------------------------------\rPosted by: vpFREE3355 <vpfree3355@gmail.com>\r------------------------------------\rvpFREE Links: http://www.west-point.org/users/usma1955/20228/V/Links.htm\r------------------------------------\rYahoo Groups Links\r<*> To visit your group on the web, go to:\rhttp://groups.yahoo.com/group/vpFREE/\r<*> Your email settings:\rIndividual Email | Traditional\r<*> To change settings online go to:\rhttp://groups.yahoo.com/group/vpFREE/join\r(Yahoo! ID required)\r<*> To change settings via email:\rvpFREE-digest@yahoogroups.com vpFREE-fullfeatured@yahoogroups.com\r<*> To unsubscribe from this group, send an email to:\rvpFREE-unsubscribe@yahoogroups.com\r<*> Your use of Yahoo Groups is subject to:\rhttps://info.yahoo.com/legal/us/yahoo/utos/terms/", "source": "Poker Master"}